README.rst
setup.cfg
setup.py
bin/rabbit_droppings
rabbit_droppings/__init__.py
rabbit_droppings/message.py
rabbit_droppings/pika_message.py
rabbit_droppings/queue.py
rabbit_droppings/rabbit.py
rabbit_droppings/rabbit_config.py
rabbit_droppings/reader.py
rabbit_droppings/writer.py
rabbit_droppings.egg-info/PKG-INFO
rabbit_droppings.egg-info/SOURCES.txt
rabbit_droppings.egg-info/dependency_links.txt
rabbit_droppings.egg-info/requires.txt
rabbit_droppings.egg-info/top_level.txt