Metadata-Version: 1.0
Name: rabbit-droppings
Version: 0.4.0
Summary: Backup/Restore RabbitMQ queues
Home-page: https://github.com/wconrad/rabbit_droppings
Author: Wayne Conrad
Author-email: kf7qga@gmail.com
License: UNKNOWN
Keywords: rabbit rabbitmq backup restore
Platform: UNKNOWN
